foliant/cli/init/__init__.py
foliant/cli/init/templates/base/Dockerfile
foliant/cli/init/templates/base/Makefile
foliant/cli/init/templates/base/README.md
foliant/cli/init/templates/base/docker-compose.yml
foliant/cli/init/templates/base/foliant.yml
foliant/cli/init/templates/base/requirements.txt
foliant/cli/init/templates/base/src/index.md
foliantcontrib.init-1.0.10.dist-info/LICENSE
foliantcontrib.init-1.0.10.dist-info/METADATA
foliantcontrib.init-1.0.10.dist-info/WHEEL
foliantcontrib.init-1.0.10.dist-info/top_level.txt
foliantcontrib.init-1.0.10.dist-info/RECORD
