Metadata-Version: 2.1
Name: foliantcontrib.init
Version: 1.0.10
Summary: Create Foliant projects from templates.
Home-page: https://github.com/foliant-docs/foliantcontrib.init
Author: Konstantin Molchanov
Author-email: moigagoo@live.com
License: MIT
Platform: any
Classifier: Development Status :: 5 - Production/Stable
Classifier: Environment :: Console
Classifier: Intended Audience :: Developers
Classifier: License :: OSI Approved :: MIT License
Classifier: Operating System :: OS Independent
Classifier: Programming Language :: Python
Classifier: Topic :: Documentation
Classifier: Topic :: Utilities
License-File: LICENSE
Requires-Dist: foliant (>=1.0.8)
Requires-Dist: python-slugify
Requires-Dist: validators
Requires-Dist: gitpython
Requires-Dist: cliar
